dingsda/__init__.py
dingsda/core.py
dingsda/date.py
dingsda/debug.py
dingsda/errors.py
dingsda/expr.py
dingsda/helpers.py
dingsda/lazy.py
dingsda/numbers.py
dingsda/string.py
dingsda/version.py
dingsda/lib/__init__.py
dingsda/lib/binary.py
dingsda/lib/bitstream.py
dingsda/lib/containers.py
dingsda/lib/hex.py
dingsda/lib/py3compat.py
dingsda-0.2.1.dist-info/F
dingsda-0.2.1.dist-info/F2
dingsda-0.2.1.dist-info/LICENSE
dingsda-0.2.1.dist-info/METADATA
dingsda-0.2.1.dist-info/WHEEL
dingsda-0.2.1.dist-info/top_level.txt
dingsda-0.2.1.dist-info/RECORD
