Metadata-Version: 2.1
Name: dingsda
Version: 0.2.1
Summary: A powerful declarative symmetric parser/builder for binary data with XML de- and encoding
Home-page: http://dingsda.readthedocs.org
Author: Tim Blume
Author-email: dingsda@3nd.io
License: MIT
Project-URL: Source, https://github.com/ev1313/dingsda
Project-URL: Documentation, https://dingsda.readthedocs.io/en/latest/
Project-URL: Issues, https://github.com/ev1313/dingsda/issues
Keywords: dingsda,construct,declarative,data structure,struct,binary,symmetric,parser,builder,parsing,building,pack,unpack,packer,unpacker,xml
Platform: POSIX
Platform: Windows
Classifier: Development Status :: 5 - Production/Stable
Classifier: License :: OSI Approved :: MIT License
Classifier: Intended Audience :: Developers
Classifier: Topic :: Software Development :: Libraries :: Python Modules
Classifier: Topic :: Software Development :: Build Tools
Classifier: Programming Language :: Python :: 3
Classifier: Programming Language :: Python :: 3.10
Classifier: Programming Language :: Python :: 3.11
Classifier: Programming Language :: Python :: Implementation :: PyPy
Requires-Python: >=3.10
License-File: LICENSE
Provides-Extra: extras
Requires-Dist: enum34 ; extra == 'extras'
Requires-Dist: numpy ; extra == 'extras'
Requires-Dist: arrow ; extra == 'extras'
Requires-Dist: ruamel.yaml ; extra == 'extras'
Requires-Dist: lz4 ; extra == 'extras'
Requires-Dist: cryptography ; extra == 'extras'
